lifestream.py
transactions.py
lifestream-0.0.18.dist-info/LICENSE.txt
lifestream-0.0.18.dist-info/METADATA
lifestream-0.0.18.dist-info/WHEEL
lifestream-0.0.18.dist-info/top_level.txt
lifestream-0.0.18.dist-info/RECORD
