Metadata-Version: 2.1
Name: lifestream
Version: 0.0.18
Summary: The fastest way to make sense of a transaction log.
Home-page: https://github.com/invictus2010/lifestream
Author: Jeff Withington
Author-email: jeffrey.withington@gmail.com
License: UNKNOWN
Platform: UNKNOWN
Classifier: Programming Language :: Python :: 3
Classifier: Programming Language :: Python :: 3.7
Classifier: Intended Audience :: Information Technology
Classifier: Intended Audience :: Financial and Insurance Industry
Classifier: License :: OSI Approved :: MIT License
Classifier: Topic :: Office/Business
Classifier: Topic :: Office/Business :: Financial
Classifier: Topic :: Internet :: Log Analysis
Requires-Dist: pandas
Requires-Dist: matplotlib
Requires-Dist: numpy
Requires-Dist: datetime
Requires-Dist: plotly
